[
  {
    "name": "Baseball",
    "type": "Vertical",
    "image": "36.jpg",
    "caption": "Caption #20"
  },
  {
    "name": "Baseball Proceso",
    "type": "Vertical",
    "image": "35.jpg",
    "caption": "Caption #20"
  },
  {
    "name": "Poses 2",
    "type": "Vertical",
    "image": "32.jpg",
    "caption": "Caption #20"
  },
  {
    "name": "Taf",
    "type": "Vertical",
    "image": "30.jpg",
    "caption": "Caption #19"
  },
  {
    "name": "Poses",
    "type": "Vertical",
    "image": "29.jpg",
    "caption": "Caption #18"
  },
  {
    "name": "Daft Punk",
    "type": "Vertical",
    "image": "26.jpg",
    "caption": "Caption #17"
  },
  {
    "name": "Blue World",
    "type": "Vertical",
    "image": "25.jpg",
    "caption": "Caption #16"
  },
  {
    "name": "RedBull BDG 2019",
    "type": "Vertical",
    "image": "23.png",
    "caption": "Caption #15"
  },
  {
    "name": "PumaXAczino",
    "type": "Vertical",
    "image": "22.jpg",
    "caption": "Caption #14"
  },
  {
    "name": "Tyler the creator",
    "type": "Vertical",
    "image": "21.jpg",
    "caption": "Caption #13"
  },
  {
    "name": "TedX",
    "type": "Vertical",
    "image": "20b.jpg",
    "caption": "Caption #12"
  },
  {
    "name": "King of nowere",
    "type": "Vertical",
    "image": "20.jpg",
    "caption": "Caption #11"
  },
  {
    "name": "WakeUp",
    "type": "Vertical",
    "image": "19.jpg",
    "caption": "Caption #10"
  },
  {
    "name": "Innvictus",
    "type": "Vertical",
    "image": "17.jpg",
    "caption": "Caption #9"
  },
  {
    "name": "Honey, no estas",
    "type": "Vertical",
    "image": "16.jpg",
    "caption": "Caption #8"
  },
  {
    "name": "Catrina",
    "type": "Vertical",
    "image": "12.jpg",
    "caption": "Caption #7"
  },
  {
    "name": "Invencible",
    "type": "Vertical",
    "image": "11.jpg",
    "caption": "Caption #6"
  },
  {
    "name": "Beatles",
    "type": "Vertical",
    "image": "10.jpg",
    "caption": "Caption #5"
  },
  {
    "name": "Gera Mx",
    "type": "Vertical",
    "image": "9.jpg",
    "caption": "Caption #4"
  },
  {
    "name": "Lagartos",
    "type": "Vertical",
    "image": "8.jpg",
    "caption": "Caption #3"
  },
  {
    "name": "FILIJ 38",
    "type": "Vertical",
    "image": "6b.jpg",
    "caption": "Caption #2"
  },
  {
    "name": "Cyberpunk",
    "type": "Vertical",
    "image": "3.jpg",
    "caption": "Caption #1"
  }
]
